<?xml version='1.0' encoding='UTF-8'?>
<taxonomyPackage xmlns="http://xbrl.org/2016/taxonomy-package" xml:lang="en">
  <identifier>https://xbrl.frc.org.uk/fr/2024-01-01/v1-0-0</identifier>
  <name>FRC 2024 Taxonomy</name>
  <version>1.0.0</version>
  <entryPoints>
    <entryPoint>
      <name>FRS-101</name>
      <entryPointDocument href="https://xbrl.frc.org.uk/FRS-101/2024-01-01/FRS-101-2024-01-01.xsd"/>
    </entryPoint>
    <entryPoint>
      <name>FRS-102</name>
      <entryPointDocument href="https://xbrl.frc.org.uk/FRS-102/2024-01-01/FRS-102-2024-01-01.xsd"/>
    </entryPoint>
    <entryPoint>
      <name>IFRS</name>
      <entryPointDocument href="https://xbrl.frc.org.uk/IFRS/2024-01-01/IFRS-2024-01-01.xsd"/>
    </entryPoint>
    <entryPoint>
      <name>Core Full</name>
      <entryPointDocument href="https://xbrl.frc.org.uk/fr/2024-01-01/core/frc-core-full-2024-01-01.xsd"/>
    </entryPoint>
    <entryPoint>
      <name>Core</name>
      <entryPointDocument href="https://xbrl.frc.org.uk/fr/2024-01-01/core/frc-core-2024-01-01.xsd"/>
    </entryPoint>
    <entryPoint>
      <name>FRS-102-UKSEF</name>
      <entryPointDocument href="https://xbrl.frc.org.uk/FRS-102/2024-01-01/UKSEF/FRS-102-2024-01-01.xsd"/>
    </entryPoint>
    <entryPoint>
      <name>IFRS-UKSEF</name>
      <entryPointDocument href="https://xbrl.frc.org.uk/IFRS/2024-01-01/UKSEF/IFRS-2024-01-01.xsd"/>
    </entryPoint>
    <entryPoint>
      <name>DPL</name>
      <entryPointDocument href="https://xbrl.frc.org.uk/dpl/2024-01-01/dpl-2024-01-01.xsd"/>
    </entryPoint>
  </entryPoints>
</taxonomyPackage>
