[
  {
    "elr": "http://xbrl.frc.org.uk/cic/roles/ShortCIC34Report",
    "definition": "111 - Short CIC 34 Report",
    "numeric_part": 111,
    "root_tree": [
      {
        "tree_id": "0000",
        "uuid": "f0473bbe-67e8-4bf4-81b3-5daffac70acf",
        "qname": "cic:ShortCIC34ReportHeading",
        "name": "Short CIC 34 report [heading]",
        "xbrl_type": "headingItemType",
        "full_type": "types:headingItemType",
        "label_cy": "Adroddiad CIC 34 byr [pennawd]",
        "substitution_group": "xbrli:item",
        "concept_id": "cic:ShortCIC34ReportHeading",
        "abstract": true,
        "children": [
          {
            "tree_id": "0000-0000",
            "uuid": "3f62fae5-35fb-4a10-9f8d-2eb5433bdac5",
            "qname": "cic:EntityElectsToCompleteDetailedCIC34ReportTruefalse",
            "name": "Entity elects to complete Detailed CIC 34 report [true/false]",
            "xbrl_type": "booleanItemType",
            "full_type": "xbrli:booleanItemType",
            "label_cy": "Mae'r endid yn dewis cwblhau adroddiad CIC 34 Manwl [gwir/anwir]",
            "substitution_group": "xbrli:item",
            "concept_id": "cic:EntityElectsToCompleteDetailedCIC34ReportTruefalse",
            "abstract": false,
            "children": []
          },
          {
            "tree_id": "0000-0001",
            "uuid": "78ea6ab8-9353-46cb-93ca-3eb4934c95d5",
            "qname": "bus:EntityInformationHeading",
            "name": "Entity information [heading]",
            "xbrl_type": "headingItemType",
            "full_type": "types:headingItemType",
            "label_cy": "Gwybodaeth am yr endid [pennawd]",
            "substitution_group": "xbrli:item",
            "concept_id": "bus:EntityInformationHeading",
            "abstract": true,
            "children": [
              {
                "tree_id": "0000-0001-0000",
                "uuid": "34db1761-8160-481a-96fd-6602a9bfca94",
                "qname": "bus:EntityCurrentLegalOrRegisteredName",
                "name": "Entity current legal or registered name",
                "xbrl_type": "stringItemType",
                "full_type": "xbrli:stringItemType",
                "label_cy": "Enw cyfreithiol neu gofrestredig presennol yr endid",
                "substitution_group": "xbrli:item",
                "concept_id": "bus:EntityCurrentLegalOrRegisteredName",
                "abstract": false,
                "children": []
              },
              {
                "tree_id": "0000-0001-0001",
                "uuid": "35f72242-04bc-470c-b4f6-a5d0a43aec09",
                "qname": "bus:UKCompaniesHouseRegisteredNumber",
                "name": "UK Companies House registered number",
                "xbrl_type": "stringItemType",
                "full_type": "xbrli:stringItemType",
                "label_cy": "Rhif cofrestredig Tŷ'r Cwmnïau yn y DU",
                "substitution_group": "xbrli:item",
                "concept_id": "bus:UKCompaniesHouseRegisteredNumber",
                "abstract": false,
                "children": []
              },
              {
                "tree_id": "0000-0001-0002",
                "uuid": "f7cf8e9a-f35c-4b5f-acd1-6c777a599f9b",
                "qname": "bus:EndDateForPeriodCoveredByReport",
                "name": "End date for period covered by report",
                "xbrl_type": "dateItemType",
                "full_type": "xbrli:dateItemType",
                "label_cy": "Dyddiad terfyn cyfnod yr adroddiad",
                "substitution_group": "xbrli:item",
                "concept_id": "bus:EndDateForPeriodCoveredByReport",
                "abstract": false,
                "children": []
              }
            ]
          },
          {
            "tree_id": "0000-0002",
            "uuid": "7ea9aa48-4561-4f06-8b14-cd3f9a30c7b1",
            "qname": "bus:EntityOfficersIncludingDirectorsPartnersHeading",
            "name": "Entity officers, including directors and partners [heading]",
            "xbrl_type": "headingItemType",
            "full_type": "types:headingItemType",
            "label_cy": "Swyddogion yr endid, yn cynnwys cyfarwyddwyr a phartneriaid [pennawd]",
            "substitution_group": "xbrli:item",
            "concept_id": "bus:EntityOfficersIncludingDirectorsPartnersHeading",
            "abstract": true,
            "children": [
              {
                "tree_id": "0000-0002-0000",
                "uuid": "d9325301-f9f5-4f5d-a760-4586fd631ccc",
                "qname": "bus:NameEntityOfficer",
                "name": "Name of entity officer",
                "xbrl_type": "stringItemType",
                "full_type": "xbrli:stringItemType",
                "label_cy": "Enw Swyddog yr endid",
                "substitution_group": "xbrli:item",
                "concept_id": "bus:NameEntityOfficer",
                "abstract": false,
                "children": []
              },
              {
                "tree_id": "0000-0002-0001",
                "uuid": "ef3eda7c-c1e2-4a6a-a345-209274817c85",
                "qname": "cic:UseNameEntityOfficerItemToIdentifyOfficerForDirectorsRemunerationSectionSignatorySectionGuidance",
                "name": "Use name of entity officer item to identify officer for Directors' remuneration section and Signatory section [guidance]",
                "xbrl_type": "guidanceItemType",
                "full_type": "types:guidanceItemType",
                "label_cy": "Defnyddiwch enw'r eitem swyddog endid i nodi swyddog ar gyfer adran cydnabyddiaeth y Cyfarwyddwyr a'r adran Llofnodwr [canllawiau]",
                "substitution_group": "xbrli:item",
                "concept_id": "cic:UseNameEntityOfficerItemToIdentifyOfficerForDirectorsRemunerationSectionSignatorySectionGuidance",
                "abstract": true,
                "children": []
              },
              {
                "tree_id": "0000-0002-0002",
                "uuid": "547c1381-ebb2-44de-8b3f-ede2205c5f56",
                "qname": "bus:UseEntityOfficersDimensionToIdentifyPositionEntityOfficerGuidance",
                "name": "Use entity officers dimension to identify position of entity officer [guidance]",
                "xbrl_type": "guidanceItemType",
                "full_type": "types:guidanceItemType",
                "label_cy": "Defnyddiwch ddimensiwn swyddogion endid i enwi swydd swyddog yr endid [canllawiau]",
                "substitution_group": "xbrli:item",
                "concept_id": "bus:UseEntityOfficersDimensionToIdentifyPositionEntityOfficerGuidance",
                "abstract": true,
                "children": []
              },
              {
                "tree_id": "0000-0002-0003",
                "uuid": "60a2063c-a5fe-4009-8df9-47f8f02504f1",
                "qname": "bus:UseEntityOfficerStatusDimensionToIdentifyExecutiveOrNon-executiveStatusGuidance",
                "name": "Use entity officer status dimension to identify executive or non-executive status [guidance]",
                "xbrl_type": "guidanceItemType",
                "full_type": "types:guidanceItemType",
                "label_cy": "Defnyddiwch dimensiwn statws swyddog yr endid i enwi statws gweithredol neu anweithredol [canllawiau]",
                "substitution_group": "xbrli:item",
                "concept_id": "bus:UseEntityOfficerStatusDimensionToIdentifyExecutiveOrNon-executiveStatusGuidance",
                "abstract": true,
                "children": []
              }
            ]
          },
          {
            "tree_id": "0000-0003",
            "uuid": "ad869367-99d9-4d6d-81db-e7f9574b5721",
            "qname": "cic:GeneralDescriptionCompanysActivitiesImpactHeading",
            "name": "General Description of the company's activities and impact [heading]",
            "xbrl_type": "headingItemType",
            "full_type": "types:headingItemType",
            "label_cy": "Disgrifiad Cyffredinol o weithgareddau'r cwmni a'i effaith [pennawd]",
            "substitution_group": "xbrli:item",
            "concept_id": "cic:GeneralDescriptionCompanysActivitiesImpactHeading",
            "abstract": true,
            "children": [
              {
                "tree_id": "0000-0003-0000",
                "uuid": "1b9a991d-2a50-4006-80b0-03b5a7331bb7",
                "qname": "bus:DescriptionPrincipalActivities",
                "name": "Description of principal activities",
                "xbrl_type": "stringItemType",
                "full_type": "xbrli:stringItemType",
                "label_cy": "Disgrifiad o'r prif weithgareddau",
                "substitution_group": "xbrli:item",
                "concept_id": "bus:DescriptionPrincipalActivities",
                "abstract": false,
                "children": []
              }
            ]
          },
          {
            "tree_id": "0000-0004",
            "uuid": "8b685f20-c574-4504-99fd-e54f382fb816",
            "qname": "cic:ConsultationWithStakeholdersHeading",
            "name": "Consultation with stakeholders [heading]",
            "xbrl_type": "headingItemType",
            "full_type": "types:headingItemType",
            "label_cy": "Ymgynghori â rhanddeiliaid [pennawd]",
            "substitution_group": "xbrli:item",
            "concept_id": "cic:ConsultationWithStakeholdersHeading",
            "abstract": true,
            "children": [
              {
                "tree_id": "0000-0004-0000",
                "uuid": "1ab2e4cb-cd9b-444a-9240-60516b4aa17b",
                "qname": "cic:ConsultationHasBeenHeldTruefalse",
                "name": "Consultation has been held [true/false]",
                "xbrl_type": "booleanItemType",
                "full_type": "xbrli:booleanItemType",
                "label_cy": "Cynhaliwyd ymgynghoriad [gwir/anwir]",
                "substitution_group": "xbrli:item",
                "concept_id": "cic:ConsultationHasBeenHeldTruefalse",
                "abstract": false,
                "children": []
              },
              {
                "tree_id": "0000-0004-0001",
                "uuid": "48e0fb94-8894-46f1-be79-282998f78d4f",
                "qname": "cic:NamesCompanyStakeholders",
                "name": "Names of company stakeholders",
                "xbrl_type": "stringItemType",
                "full_type": "xbrli:stringItemType",
                "label_cy": "Enwau rhanddeiliaid y cwmni",
                "substitution_group": "xbrli:item",
                "concept_id": "cic:NamesCompanyStakeholders",
                "abstract": false,
                "children": []
              },
              {
                "tree_id": "0000-0004-0002",
                "uuid": "ce12db64-104b-4637-927b-58e3235cde63",
                "qname": "cic:DescriptionHowStakeholdersHaveBeenConsulted",
                "name": "Description of how the stakeholders have been consulted",
                "xbrl_type": "stringItemType",
                "full_type": "xbrli:stringItemType",
                "label_cy": "Disgrifiad o sut yr ymgynghorwyd â'r rhanddeiliaid",
                "substitution_group": "xbrli:item",
                "concept_id": "cic:DescriptionHowStakeholdersHaveBeenConsulted",
                "abstract": false,
                "children": []
              },
              {
                "tree_id": "0000-0004-0003",
                "uuid": "3e81e66b-dd6f-47df-ba8b-a438fb40a3ef",
                "qname": "cic:DescriptionActionsTakenInResponseToStakeholderConsultation",
                "name": "Description of actions taken in response to stakeholder consultation",
                "xbrl_type": "stringItemType",
                "full_type": "xbrli:stringItemType",
                "label_cy": "Disgrifiad o'r camau a gymerwyd mewn ymateb i'r ymgynghoriad â rhanddeiliaid",
                "substitution_group": "xbrli:item",
                "concept_id": "cic:DescriptionActionsTakenInResponseToStakeholderConsultation",
                "abstract": false,
                "children": []
              }
            ]
          },
          {
            "tree_id": "0000-0005",
            "uuid": "c05444a3-30fd-4fcd-8e02-5aacb83b8189",
            "qname": "direp:DirectorsRemunerationHeading",
            "name": "Directors' remuneration [heading]",
            "xbrl_type": "headingItemType",
            "full_type": "types:headingItemType",
            "label_cy": "Cydnabyddiaeth cyfarwyddwr [pennawd]",
            "substitution_group": "xbrli:item",
            "concept_id": "direp:DirectorsRemunerationHeading",
            "abstract": true,
            "children": [
              {
                "tree_id": "0000-0005-0000",
                "uuid": "01a899ba-cadb-4137-9ef7-6da7c49c42d4",
                "qname": "cic:RemunerationWasReceivedByDirectorsTruefalse",
                "name": "Remuneration was received by the directors [true/false]",
                "xbrl_type": "booleanItemType",
                "full_type": "xbrli:booleanItemType",
                "label_cy": "Derbyniwyd tâl gan y cyfarwyddwyr [gwir/anwir]",
                "substitution_group": "xbrli:item",
                "concept_id": "cic:RemunerationWasReceivedByDirectorsTruefalse",
                "abstract": false,
                "children": []
              },
              {
                "tree_id": "0000-0005-0001",
                "uuid": "a90787b9-9c32-49fa-a16e-74a8223e86de",
                "qname": "direp:DirectorRemunerationBenefitsIncludingPaymentsToThirdParties",
                "name": "Director remuneration and benefits including payments to third parties",
                "xbrl_type": "monetaryItemType",
                "full_type": "xbrli:monetaryItemType",
                "label_cy": "Cydnabyddiaeth a buddion cyfarwyddwr yn cynnwys taliadau i drydydd partïon",
                "substitution_group": "xbrli:item",
                "concept_id": "direp:DirectorRemunerationBenefitsIncludingPaymentsToThirdParties",
                "abstract": false,
                "children": []
              }
            ]
          },
          {
            "tree_id": "0000-0006",
            "uuid": "7514c202-e470-41a9-98e8-dc9a19330d3a",
            "qname": "cic:TransferAssetsOtherThanForFullConsiderationHeading",
            "name": "Transfer of assets other than for full consideration [heading]",
            "xbrl_type": "headingItemType",
            "full_type": "types:headingItemType",
            "label_cy": "Trosglwyddo asedau ac eithrio ar gyfer ystyriaeth lawn [pennawd]",
            "substitution_group": "xbrli:item",
            "concept_id": "cic:TransferAssetsOtherThanForFullConsiderationHeading",
            "abstract": true,
            "children": [
              {
                "tree_id": "0000-0006-0000",
                "uuid": "bdb37c49-be01-4b4b-bfba-c8b1ce3bfd68",
                "qname": "cic:TransfersAssetsOtherThanForFullConsiderationHaveBeenMadeTruefalse",
                "name": "Transfers of assets other than for full consideration have been made [true/false]",
                "xbrl_type": "booleanItemType",
                "full_type": "xbrli:booleanItemType",
                "label_cy": "Trosglwyddiadau asedau, ac eithrio ar gyfer ystyriaeth lawn, wedi'u gwneud [gwir/anwir]",
                "substitution_group": "xbrli:item",
                "concept_id": "cic:TransfersAssetsOtherThanForFullConsiderationHaveBeenMadeTruefalse",
                "abstract": false,
                "children": []
              },
              {
                "tree_id": "0000-0006-0001",
                "uuid": "c266acc8-3c2f-4b5e-a1cf-614b0139c2a2",
                "qname": "cic:DescriptionDetailsAnyTransferAssetsOtherThanForFullConsiderationToAnAssetLockedBodyOrForBenefitCommunity",
                "name": "Description of details of any transfer of assets other than for full consideration to an asset locked body or for the benefit of the community",
                "xbrl_type": "stringItemType",
                "full_type": "xbrli:stringItemType",
                "label_cy": "Disgrifiad o fanylion unrhyw asedau a drosglwyddwyd, ac eithrio ar gyfer ystyriaeth lawn, i gorff ag asedau wedi'u cloi, neu er budd y gymuned",
                "substitution_group": "xbrli:item",
                "concept_id": "cic:DescriptionDetailsAnyTransferAssetsOtherThanForFullConsiderationToAnAssetLockedBodyOrForBenefitCommunity",
                "abstract": false,
                "children": []
              }
            ]
          },
          {
            "tree_id": "0000-0007",
            "uuid": "d6480c89-c954-440e-bfdf-9d493d9cdf40",
            "qname": "cic:SignatoryHeading",
            "name": "Signatory [heading]",
            "xbrl_type": "headingItemType",
            "full_type": "types:headingItemType",
            "label_cy": "Llofnodwr [pennawd]",
            "substitution_group": "xbrli:item",
            "concept_id": "cic:SignatoryHeading",
            "abstract": true,
            "children": [
              {
                "tree_id": "0000-0007-0000",
                "uuid": "59dd4b08-3c5c-4943-ab95-975f1836f0b7",
                "qname": "cic:DirectorSigningCIC34Report",
                "name": "Director signing CIC 34 Report",
                "xbrl_type": "fixedItemType",
                "full_type": "types:fixedItemType",
                "label_cy": "Cyfarwyddwr sy'n llofnodi Adroddiad CIC 34",
                "substitution_group": "xbrli:item",
                "concept_id": "cic:DirectorSigningCIC34Report",
                "abstract": false,
                "children": []
              },
              {
                "tree_id": "0000-0007-0001",
                "uuid": "a47b96b7-359d-4e48-85ea-251e7d666424",
                "qname": "cic:DateSigningCIC34Report",
                "name": "Date of signing of CIC 34 Report",
                "xbrl_type": "dateItemType",
                "full_type": "xbrli:dateItemType",
                "label_cy": "Dyddiad llofnodi Adroddiad CIC 34",
                "substitution_group": "xbrli:item",
                "concept_id": "cic:DateSigningCIC34Report",
                "abstract": false,
                "children": []
              }
            ]
          }
        ]
      }
    ]
  },
  {
    "elr": "http://xbrl.frc.org.uk/cic/roles/DetailedCIC34Report",
    "definition": "112 - Detailed CIC 34 Report",
    "numeric_part": 112,
    "root_tree": [
      {
        "tree_id": "0000",
        "uuid": "87f34a48-5345-45c8-93a7-79de68b0b3d8",
        "qname": "cic:DetailedCIC34ReportHeading",
        "name": "Detailed CIC 34 report [heading]",
        "xbrl_type": "headingItemType",
        "full_type": "types:headingItemType",
        "label_cy": "Adroddiad CIC 34 manwl [pennawd]",
        "substitution_group": "xbrli:item",
        "concept_id": "cic:DetailedCIC34ReportHeading",
        "abstract": true,
        "children": [
          {
            "tree_id": "0000-0000",
            "uuid": "66b93c67-cbb7-44ff-a528-c6f27b4dd571",
            "qname": "cic:EntityElectsToCompleteDetailedCIC34ReportTruefalse",
            "name": "Entity elects to complete Detailed CIC 34 report [true/false]",
            "xbrl_type": "booleanItemType",
            "full_type": "xbrli:booleanItemType",
            "label_cy": "Mae'r endid yn dewis cwblhau adroddiad CIC 34 Manwl [gwir/anwir]",
            "substitution_group": "xbrli:item",
            "concept_id": "cic:EntityElectsToCompleteDetailedCIC34ReportTruefalse",
            "abstract": false,
            "children": []
          },
          {
            "tree_id": "0000-0001",
            "uuid": "e312882f-a980-4645-8242-469d470cc0d3",
            "qname": "bus:EntityInformationHeading",
            "name": "Entity information [heading]",
            "xbrl_type": "headingItemType",
            "full_type": "types:headingItemType",
            "label_cy": "Gwybodaeth am yr endid [pennawd]",
            "substitution_group": "xbrli:item",
            "concept_id": "bus:EntityInformationHeading",
            "abstract": true,
            "children": [
              {
                "tree_id": "0000-0001-0000",
                "uuid": "ba6f6e6f-5ce2-40cf-b84a-ebd0cbdf84bc",
                "qname": "bus:EntityCurrentLegalOrRegisteredName",
                "name": "Entity current legal or registered name",
                "xbrl_type": "stringItemType",
                "full_type": "xbrli:stringItemType",
                "label_cy": "Enw cyfreithiol neu gofrestredig presennol yr endid",
                "substitution_group": "xbrli:item",
                "concept_id": "bus:EntityCurrentLegalOrRegisteredName",
                "abstract": false,
                "children": []
              },
              {
                "tree_id": "0000-0001-0001",
                "uuid": "7feadabb-dc7d-4b24-a3f0-5cd9fdf78bec",
                "qname": "bus:UKCompaniesHouseRegisteredNumber",
                "name": "UK Companies House registered number",
                "xbrl_type": "stringItemType",
                "full_type": "xbrli:stringItemType",
                "label_cy": "Rhif cofrestredig Tŷ'r Cwmnïau yn y DU",
                "substitution_group": "xbrli:item",
                "concept_id": "bus:UKCompaniesHouseRegisteredNumber",
                "abstract": false,
                "children": []
              },
              {
                "tree_id": "0000-0001-0002",
                "uuid": "31af2050-136d-4e69-aa97-898ef5a897ce",
                "qname": "bus:EndDateForPeriodCoveredByReport",
                "name": "End date for period covered by report",
                "xbrl_type": "dateItemType",
                "full_type": "xbrli:dateItemType",
                "label_cy": "Dyddiad terfyn cyfnod yr adroddiad",
                "substitution_group": "xbrli:item",
                "concept_id": "bus:EndDateForPeriodCoveredByReport",
                "abstract": false,
                "children": []
              }
            ]
          },
          {
            "tree_id": "0000-0002",
            "uuid": "c311de9f-e0fe-4a2c-a4a1-d81cdb98fb0e",
            "qname": "bus:EntityOfficersIncludingDirectorsPartnersHeading",
            "name": "Entity officers, including directors and partners [heading]",
            "xbrl_type": "headingItemType",
            "full_type": "types:headingItemType",
            "label_cy": "Swyddogion yr endid, yn cynnwys cyfarwyddwyr a phartneriaid [pennawd]",
            "substitution_group": "xbrli:item",
            "concept_id": "bus:EntityOfficersIncludingDirectorsPartnersHeading",
            "abstract": true,
            "children": [
              {
                "tree_id": "0000-0002-0000",
                "uuid": "eebe104a-25e0-4429-80de-8692c034c4ae",
                "qname": "bus:NameEntityOfficer",
                "name": "Name of entity officer",
                "xbrl_type": "stringItemType",
                "full_type": "xbrli:stringItemType",
                "label_cy": "Enw Swyddog yr endid",
                "substitution_group": "xbrli:item",
                "concept_id": "bus:NameEntityOfficer",
                "abstract": false,
                "children": []
              },
              {
                "tree_id": "0000-0002-0001",
                "uuid": "259e7ffb-18ef-4ae5-9ba2-5c7022f4ecaa",
                "qname": "cic:UseNameEntityOfficerItemToIdentifyOfficerForDirectorsRemunerationSectionSignatorySectionGuidance",
                "name": "Use name of entity officer item to identify officer for Directors' remuneration section and Signatory section [guidance]",
                "xbrl_type": "guidanceItemType",
                "full_type": "types:guidanceItemType",
                "label_cy": "Defnyddiwch enw'r eitem swyddog endid i nodi swyddog ar gyfer adran cydnabyddiaeth y Cyfarwyddwyr a'r adran Llofnodwr [canllawiau]",
                "substitution_group": "xbrli:item",
                "concept_id": "cic:UseNameEntityOfficerItemToIdentifyOfficerForDirectorsRemunerationSectionSignatorySectionGuidance",
                "abstract": true,
                "children": []
              },
              {
                "tree_id": "0000-0002-0002",
                "uuid": "5b452c9c-9c43-4e67-aaa4-4d2ca9409f67",
                "qname": "bus:UseEntityOfficersDimensionToIdentifyPositionEntityOfficerGuidance",
                "name": "Use entity officers dimension to identify position of entity officer [guidance]",
                "xbrl_type": "guidanceItemType",
                "full_type": "types:guidanceItemType",
                "label_cy": "Defnyddiwch ddimensiwn swyddogion endid i enwi swydd swyddog yr endid [canllawiau]",
                "substitution_group": "xbrli:item",
                "concept_id": "bus:UseEntityOfficersDimensionToIdentifyPositionEntityOfficerGuidance",
                "abstract": true,
                "children": []
              },
              {
                "tree_id": "0000-0002-0003",
                "uuid": "af8af6ea-c8fc-4ced-9d15-bc1b8fcf48c7",
                "qname": "bus:UseEntityOfficerStatusDimensionToIdentifyExecutiveOrNon-executiveStatusGuidance",
                "name": "Use entity officer status dimension to identify executive or non-executive status [guidance]",
                "xbrl_type": "guidanceItemType",
                "full_type": "types:guidanceItemType",
                "label_cy": "Defnyddiwch dimensiwn statws swyddog yr endid i enwi statws gweithredol neu anweithredol [canllawiau]",
                "substitution_group": "xbrli:item",
                "concept_id": "bus:UseEntityOfficerStatusDimensionToIdentifyExecutiveOrNon-executiveStatusGuidance",
                "abstract": true,
                "children": []
              }
            ]
          },
          {
            "tree_id": "0000-0003",
            "uuid": "b345d453-8bc6-40e3-8bd5-c84c35707883",
            "qname": "cic:GeneralDescriptionCompanysActivitiesImpactHeading",
            "name": "General Description of the company's activities and impact [heading]",
            "xbrl_type": "headingItemType",
            "full_type": "types:headingItemType",
            "label_cy": "Disgrifiad Cyffredinol o weithgareddau'r cwmni a'i effaith [pennawd]",
            "substitution_group": "xbrli:item",
            "concept_id": "cic:GeneralDescriptionCompanysActivitiesImpactHeading",
            "abstract": true,
            "children": [
              {
                "tree_id": "0000-0003-0000",
                "uuid": "a0798552-2f18-4ff7-a831-248dbc8a481d",
                "qname": "bus:DescriptionPrincipalActivities",
                "name": "Description of principal activities",
                "xbrl_type": "stringItemType",
                "full_type": "xbrli:stringItemType",
                "label_cy": "Disgrifiad o'r prif weithgareddau",
                "substitution_group": "xbrli:item",
                "concept_id": "bus:DescriptionPrincipalActivities",
                "abstract": false,
                "children": []
              }
            ]
          },
          {
            "tree_id": "0000-0004",
            "uuid": "70ae0493-8c1d-497e-9383-8c6ee6c7ce2d",
            "qname": "cic:ConsultationWithStakeholdersHeading",
            "name": "Consultation with stakeholders [heading]",
            "xbrl_type": "headingItemType",
            "full_type": "types:headingItemType",
            "label_cy": "Ymgynghori â rhanddeiliaid [pennawd]",
            "substitution_group": "xbrli:item",
            "concept_id": "cic:ConsultationWithStakeholdersHeading",
            "abstract": true,
            "children": [
              {
                "tree_id": "0000-0004-0000",
                "uuid": "e0dcb6f8-50c5-4a73-b42d-2f57c3071cf8",
                "qname": "cic:ConsultationHasBeenHeldTruefalse",
                "name": "Consultation has been held [true/false]",
                "xbrl_type": "booleanItemType",
                "full_type": "xbrli:booleanItemType",
                "label_cy": "Cynhaliwyd ymgynghoriad [gwir/anwir]",
                "substitution_group": "xbrli:item",
                "concept_id": "cic:ConsultationHasBeenHeldTruefalse",
                "abstract": false,
                "children": []
              },
              {
                "tree_id": "0000-0004-0001",
                "uuid": "8fdfcecb-9d66-421f-9596-bcc63aa3d7f3",
                "qname": "cic:NamesCompanyStakeholders",
                "name": "Names of company stakeholders",
                "xbrl_type": "stringItemType",
                "full_type": "xbrli:stringItemType",
                "label_cy": "Enwau rhanddeiliaid y cwmni",
                "substitution_group": "xbrli:item",
                "concept_id": "cic:NamesCompanyStakeholders",
                "abstract": false,
                "children": []
              },
              {
                "tree_id": "0000-0004-0002",
                "uuid": "a1a449b4-7da6-4ba6-bc1e-3e03913c8c74",
                "qname": "cic:DescriptionHowStakeholdersHaveBeenConsulted",
                "name": "Description of how the stakeholders have been consulted",
                "xbrl_type": "stringItemType",
                "full_type": "xbrli:stringItemType",
                "label_cy": "Disgrifiad o sut yr ymgynghorwyd â'r rhanddeiliaid",
                "substitution_group": "xbrli:item",
                "concept_id": "cic:DescriptionHowStakeholdersHaveBeenConsulted",
                "abstract": false,
                "children": []
              },
              {
                "tree_id": "0000-0004-0003",
                "uuid": "d3b40b7f-1a7f-4244-9796-7d8592578ff8",
                "qname": "cic:DescriptionActionsTakenInResponseToStakeholderConsultation",
                "name": "Description of actions taken in response to stakeholder consultation",
                "xbrl_type": "stringItemType",
                "full_type": "xbrli:stringItemType",
                "label_cy": "Disgrifiad o'r camau a gymerwyd mewn ymateb i'r ymgynghoriad â rhanddeiliaid",
                "substitution_group": "xbrli:item",
                "concept_id": "cic:DescriptionActionsTakenInResponseToStakeholderConsultation",
                "abstract": false,
                "children": []
              }
            ]
          },
          {
            "tree_id": "0000-0005",
            "uuid": "6c502644-0d94-4b95-85e3-646b969f2b95",
            "qname": "direp:DirectorsRemunerationHeading",
            "name": "Directors' remuneration [heading]",
            "xbrl_type": "headingItemType",
            "full_type": "types:headingItemType",
            "label_cy": "Cydnabyddiaeth cyfarwyddwr [pennawd]",
            "substitution_group": "xbrli:item",
            "concept_id": "direp:DirectorsRemunerationHeading",
            "abstract": true,
            "children": [
              {
                "tree_id": "0000-0005-0000",
                "uuid": "1280b508-be59-45df-87f0-df9318ff38cd",
                "qname": "cic:RemunerationWasReceivedByDirectorsTruefalse",
                "name": "Remuneration was received by the directors [true/false]",
                "xbrl_type": "booleanItemType",
                "full_type": "xbrli:booleanItemType",
                "label_cy": "Derbyniwyd tâl gan y cyfarwyddwyr [gwir/anwir]",
                "substitution_group": "xbrli:item",
                "concept_id": "cic:RemunerationWasReceivedByDirectorsTruefalse",
                "abstract": false,
                "children": []
              },
              {
                "tree_id": "0000-0005-0001",
                "uuid": "391c90da-e6cb-4db2-a1b7-9a98b9fda45a",
                "qname": "cic:DirectorsRemunerationAsPartAccountsHeading",
                "name": "Directors' remuneration as part of accounts [heading]",
                "xbrl_type": "headingItemType",
                "full_type": "types:headingItemType",
                "label_cy": "Tâl cyfarwyddwyr fel rhan o'r cyfrifon [pennawd]",
                "substitution_group": "xbrli:item",
                "concept_id": "cic:DirectorsRemunerationAsPartAccountsHeading",
                "abstract": true,
                "children": [
                  {
                    "tree_id": "0000-0005-0001-0000",
                    "uuid": "ff52c24a-360d-465c-b72d-6cbf21a8d832",
                    "qname": "cic:DirectorsRemunerationProvidedInAccountsTruefalse",
                    "name": "Directors' remuneration provided in accounts [true/false]",
                    "xbrl_type": "booleanItemType",
                    "full_type": "xbrli:booleanItemType",
                    "label_cy": "Tâl cyfarwyddwyr wedi'i ddarparu mewn cyfrifon [gwir/anwir]",
                    "substitution_group": "xbrli:item",
                    "concept_id": "cic:DirectorsRemunerationProvidedInAccountsTruefalse",
                    "abstract": false,
                    "children": []
                  },
                  {
                    "tree_id": "0000-0005-0001-0001",
                    "uuid": "6bf499e0-cddb-43f6-a9ce-bc11dd237f13",
                    "qname": "cic:DescriptionWhereDirectorsRemunerationInformationCanBeFoundInAccounts",
                    "name": "Description of where directors' remuneration information can be found in accounts",
                    "xbrl_type": "stringItemType",
                    "full_type": "xbrli:stringItemType",
                    "label_cy": "Disgrifiad o ble y gellir dod o hyd i wybodaeth am dâl cyfarwyddwyr yn y cyfrifon",
                    "substitution_group": "xbrli:item",
                    "concept_id": "cic:DescriptionWhereDirectorsRemunerationInformationCanBeFoundInAccounts",
                    "abstract": false,
                    "children": []
                  }
                ]
              },
              {
                "tree_id": "0000-0005-0002",
                "uuid": "427193ec-b9c0-4266-baae-decef1085af0",
                "qname": "direp:DirectorRemunerationBenefitsIncludingPaymentsToThirdParties",
                "name": "Director remuneration and benefits including payments to third parties",
                "xbrl_type": "monetaryItemType",
                "full_type": "xbrli:monetaryItemType",
                "label_cy": "Cydnabyddiaeth a buddion cyfarwyddwr yn cynnwys taliadau i drydydd partïon",
                "substitution_group": "xbrli:item",
                "concept_id": "direp:DirectorRemunerationBenefitsIncludingPaymentsToThirdParties",
                "abstract": false,
                "children": []
              },
              {
                "tree_id": "0000-0005-0003",
                "uuid": "ec992be0-98e8-4cbc-b590-e07494261b8d",
                "qname": "direp:NetAssetsReceivedOrReceivableUnderLong-termIncentiveSchemesDirectors",
                "name": "Net assets received or receivable under long-term incentive schemes, directors",
                "xbrl_type": "monetaryItemType",
                "full_type": "xbrli:monetaryItemType",
                "label_cy": "Asedau net a dderbyniwyd neu sy'n dderbyniadwy dan gynlluniau cymhelliad hirdymor, cyfarwyddwyr",
                "substitution_group": "xbrli:item",
                "concept_id": "direp:NetAssetsReceivedOrReceivableUnderLong-termIncentiveSchemesDirectors",
                "abstract": false,
                "children": []
              },
              {
                "tree_id": "0000-0005-0004",
                "uuid": "5323de21-c002-4416-b205-2ce59e7d27e5",
                "qname": "cic:OverallTotalValueAnyCompanyContributionsHeading",
                "name": "Overall total value of any company contributions [heading]",
                "xbrl_type": "headingItemType",
                "full_type": "types:headingItemType",
                "label_cy": "Cyfanswm gwerth cyffredinol unrhyw gyfraniadau gan y cwmni [pennawd]",
                "substitution_group": "xbrli:item",
                "concept_id": "cic:OverallTotalValueAnyCompanyContributionsHeading",
                "abstract": true,
                "children": [
                  {
                    "tree_id": "0000-0005-0004-0000",
                    "uuid": "fc0f308b-5e5e-4d4f-a992-dd00fc12a74f",
                    "qname": "direp:AccruedPensionPeriodEndDirectors",
                    "name": "Accrued pension at period end, directors",
                    "xbrl_type": "monetaryItemType",
                    "full_type": "xbrli:monetaryItemType",
                    "label_cy": "Pensiwn cronnus ar ddiwedd y cyfnod, cyfarwyddwyr",
                    "substitution_group": "xbrli:item",
                    "concept_id": "direp:AccruedPensionPeriodEndDirectors",
                    "abstract": false,
                    "children": []
                  },
                  {
                    "tree_id": "0000-0005-0004-0001",
                    "uuid": "8c8d596e-9ce7-41c3-b276-3771f27d9f27",
                    "qname": "direp:CompanyContributionsToDefinedBenefitPlansDirectors",
                    "name": "Company contributions to defined benefit plans, directors",
                    "xbrl_type": "monetaryItemType",
                    "full_type": "xbrli:monetaryItemType",
                    "label_cy": "Cyfraniadau'r cwmni i gynlluniau buddiannau diffiniedig, cyfarwyddwyr",
                    "substitution_group": "xbrli:item",
                    "concept_id": "direp:CompanyContributionsToDefinedBenefitPlansDirectors",
                    "abstract": false,
                    "children": []
                  }
                ]
              },
              {
                "tree_id": "0000-0005-0005",
                "uuid": "b7505026-8a8f-4c69-b187-00d46d44ef9d",
                "qname": "direp:NumberDirectorsAccruingRetirementBenefits",
                "name": "Number of directors accruing retirement benefits",
                "xbrl_type": "decimalItemType",
                "full_type": "xbrli:decimalItemType",
                "label_cy": "Nifer y cyfarwyddwyr sy'n cronni buddion ymddeoliad",
                "substitution_group": "xbrli:item",
                "concept_id": "direp:NumberDirectorsAccruingRetirementBenefits",
                "abstract": false,
                "children": [
                  {
                    "tree_id": "0000-0005-0005-0000",
                    "uuid": "513426a3-9c68-4105-b508-0ded343eaa3a",
                    "qname": "direp:NumberDirectorsAccruingBenefitsUnderDefinedBenefitScheme",
                    "name": "Number of directors accruing benefits under a defined benefit scheme",
                    "xbrl_type": "decimalItemType",
                    "full_type": "xbrli:decimalItemType",
                    "label_cy": "Nifer y cyfarwyddwyr sy'n cronni buddion o dan gynllun buddiannau diffiniedig",
                    "substitution_group": "xbrli:item",
                    "concept_id": "direp:NumberDirectorsAccruingBenefitsUnderDefinedBenefitScheme",
                    "abstract": false,
                    "children": []
                  },
                  {
                    "tree_id": "0000-0005-0005-0001",
                    "uuid": "cca30d44-c47e-46bd-84a8-6134b5689eb9",
                    "qname": "direp:NumberDirectorsAccruingBenefitsUnderMoneyPurchaseScheme",
                    "name": "Number of directors accruing benefits under a money purchase scheme",
                    "xbrl_type": "decimalItemType",
                    "full_type": "xbrli:decimalItemType",
                    "label_cy": "Nifer y cyfarwyddwyr sy'n cronni buddion o dan gynllun prynu arian",
                    "substitution_group": "xbrli:item",
                    "concept_id": "direp:NumberDirectorsAccruingBenefitsUnderMoneyPurchaseScheme",
                    "abstract": false,
                    "children": []
                  }
                ]
              },
              {
                "tree_id": "0000-0005-0006",
                "uuid": "d7e22ea4-b4f4-4657-a79e-a842b904f792",
                "qname": "direp:CompensationForLossOfficeDirectors",
                "name": "Compensation for loss of office, directors",
                "xbrl_type": "monetaryItemType",
                "full_type": "xbrli:monetaryItemType",
                "label_cy": "Iawndal am golli swyddfa, cyfarwyddwyr",
                "substitution_group": "xbrli:item",
                "concept_id": "direp:CompensationForLossOfficeDirectors",
                "abstract": false,
                "children": [
                  {
                    "tree_id": "0000-0005-0006-0000",
                    "uuid": "3288e5dd-b1de-40af-868c-c12ef79770fd",
                    "qname": "direp:DescriptionNon-cashBenefitsProvidedAsCompensationForLossOfficeDirectors",
                    "name": "Description of non-cash benefits provided as compensation for loss of office, directors",
                    "xbrl_type": "stringItemType",
                    "full_type": "xbrli:stringItemType",
                    "label_cy": "Disgrifiad o fuddiannau nad ydynt yn arian parod fel iawndal am golli swyddfa, cyfarwyddwyr",
                    "substitution_group": "xbrli:item",
                    "concept_id": "direp:DescriptionNon-cashBenefitsProvidedAsCompensationForLossOfficeDirectors",
                    "abstract": false,
                    "children": []
                  }
                ]
              },
              {
                "tree_id": "0000-0005-0007",
                "uuid": "9eca6eab-d142-4bb2-9b6a-ac4f400e80b1",
                "qname": "direp:PaymentsToThirdPartiesForDirectorsServicesHeading",
                "name": "Payments to third parties for directors' services [heading]",
                "xbrl_type": "headingItemType",
                "full_type": "types:headingItemType",
                "label_cy": "Taliadau i drydydd partïon am 'wasanaethau cyfarwyddwyr [pennawd]",
                "substitution_group": "xbrli:item",
                "concept_id": "direp:PaymentsToThirdPartiesForDirectorsServicesHeading",
                "abstract": true,
                "children": [
                  {
                    "tree_id": "0000-0005-0007-0000",
                    "uuid": "7926de25-3d85-4cf8-a9aa-a291a3455c67",
                    "qname": "direp:PaymentsMadeToThirdPartiesForServicesDirectorsAsDirectors",
                    "name": "Payments made to third parties for services of directors as directors",
                    "xbrl_type": "monetaryItemType",
                    "full_type": "xbrli:monetaryItemType",
                    "label_cy": "Taliadau i drydydd partïon am wasanaethau cyfarwyddwyr fel cyfarwyddwyr",
                    "substitution_group": "xbrli:item",
                    "concept_id": "direp:PaymentsMadeToThirdPartiesForServicesDirectorsAsDirectors",
                    "abstract": false,
                    "children": []
                  },
                  {
                    "tree_id": "0000-0005-0007-0001",
                    "uuid": "cde54404-2448-41e3-9784-29679cc7c864",
                    "qname": "direp:PaymentsMadeToThirdPartiesForServicesDirectorsWhileDirectors",
                    "name": "Payments made to third parties for services of directors while directors",
                    "xbrl_type": "monetaryItemType",
                    "full_type": "xbrli:monetaryItemType",
                    "label_cy": "Taliadau i drydydd partïon am wasanaethau cyfarwyddwyr tra'n gyfarwyddwyr",
                    "substitution_group": "xbrli:item",
                    "concept_id": "direp:PaymentsMadeToThirdPartiesForServicesDirectorsWhileDirectors",
                    "abstract": false,
                    "children": []
                  },
                  {
                    "tree_id": "0000-0005-0007-0002",
                    "uuid": "3da1fabe-e443-4e51-96f8-f1a28c740db5",
                    "qname": "direp:DescriptionNon-cashBenefitsProvidedToThirdPartiesForServicesDirectors",
                    "name": "Description of non-cash benefits provided to third parties for services of directors",
                    "xbrl_type": "stringItemType",
                    "full_type": "xbrli:stringItemType",
                    "label_cy": "Disgrifiad o fuddiannau nad ydynt yn arian parod i drydydd partïon am wasanaethau cyfarwyddwyr",
                    "substitution_group": "xbrli:item",
                    "concept_id": "direp:DescriptionNon-cashBenefitsProvidedToThirdPartiesForServicesDirectors",
                    "abstract": false,
                    "children": []
                  }
                ]
              },
              {
                "tree_id": "0000-0005-0008",
                "uuid": "a7279e62-24ba-4a93-a069-683be94d4b9d",
                "qname": "direp:DirectorsRemunerationFree-textComment",
                "name": "Directors' remuneration free-text comment",
                "xbrl_type": "stringItemType",
                "full_type": "xbrli:stringItemType",
                "label_cy": "Sylwad testun rhydd ar gydnabyddiaeth cyfarwyddwr",
                "substitution_group": "xbrli:item",
                "concept_id": "direp:DirectorsRemunerationFree-textComment",
                "abstract": false,
                "children": []
              }
            ]
          },
          {
            "tree_id": "0000-0006",
            "uuid": "ad86a85c-fc37-4851-98c6-0730e3f8652e",
            "qname": "cic:TransferAssetsOtherThanForFullConsiderationHeading",
            "name": "Transfer of assets other than for full consideration [heading]",
            "xbrl_type": "headingItemType",
            "full_type": "types:headingItemType",
            "label_cy": "Trosglwyddo asedau ac eithrio ar gyfer ystyriaeth lawn [pennawd]",
            "substitution_group": "xbrli:item",
            "concept_id": "cic:TransferAssetsOtherThanForFullConsiderationHeading",
            "abstract": true,
            "children": [
              {
                "tree_id": "0000-0006-0000",
                "uuid": "381d2856-1d30-4432-96ac-1d549ad1f58b",
                "qname": "cic:TransfersAssetsOtherThanForFullConsiderationHaveBeenMadeTruefalse",
                "name": "Transfers of assets other than for full consideration have been made [true/false]",
                "xbrl_type": "booleanItemType",
                "full_type": "xbrli:booleanItemType",
                "label_cy": "Trosglwyddiadau asedau, ac eithrio ar gyfer ystyriaeth lawn, wedi'u gwneud [gwir/anwir]",
                "substitution_group": "xbrli:item",
                "concept_id": "cic:TransfersAssetsOtherThanForFullConsiderationHaveBeenMadeTruefalse",
                "abstract": false,
                "children": []
              },
              {
                "tree_id": "0000-0006-0001",
                "uuid": "64459cff-2afb-4e0e-89b2-44be4b95564a",
                "qname": "cic:DescriptionAsset",
                "name": "Description of asset",
                "xbrl_type": "stringItemType",
                "full_type": "xbrli:stringItemType",
                "label_cy": "Disgrifiad o'r ased",
                "substitution_group": "xbrli:item",
                "concept_id": "cic:DescriptionAsset",
                "abstract": false,
                "children": []
              },
              {
                "tree_id": "0000-0006-0002",
                "uuid": "59c85e32-5bd8-4d97-9017-8934b70971e7",
                "qname": "cic:EstimatedValueAsset",
                "name": "Estimated value of asset",
                "xbrl_type": "monetaryItemType",
                "full_type": "xbrli:monetaryItemType",
                "label_cy": "Amcangyfrif o werth yr ased",
                "substitution_group": "xbrli:item",
                "concept_id": "cic:EstimatedValueAsset",
                "abstract": false,
                "children": []
              },
              {
                "tree_id": "0000-0006-0003",
                "uuid": "191adb0c-c27b-4a20-bbef-65244cd190f4",
                "qname": "cic:DescriptionRecipientToWhichAssetWasTransferred",
                "name": "Description of recipient to which the asset was transferred",
                "xbrl_type": "stringItemType",
                "full_type": "xbrli:stringItemType",
                "label_cy": "Disgrifiad o'r derbynnydd y trosglwyddwyd yr ased iddo",
                "substitution_group": "xbrli:item",
                "concept_id": "cic:DescriptionRecipientToWhichAssetWasTransferred",
                "abstract": false,
                "children": []
              },
              {
                "tree_id": "0000-0006-0004",
                "uuid": "3a1bd4db-eb5d-47b8-b306-77357764cecc",
                "qname": "cic:RecipientAnAsset-lockedBodyTruefalse",
                "name": "Recipient is an asset-locked body [true/false]",
                "xbrl_type": "booleanItemType",
                "full_type": "xbrli:booleanItemType",
                "label_cy": "Mae'r derbynnydd yn gorff sydd dan glo o ran asedau [gwir/anwir]",
                "substitution_group": "xbrli:item",
                "concept_id": "cic:RecipientAnAsset-lockedBodyTruefalse",
                "abstract": false,
                "children": []
              },
              {
                "tree_id": "0000-0006-0005",
                "uuid": "a0c0f5ce-bf35-461c-8f88-7dd1a9243fd9",
                "qname": "cic:DescriptionHowAssetWillBenefitCommunity",
                "name": "Description of how the asset will benefit the community",
                "xbrl_type": "stringItemType",
                "full_type": "xbrli:stringItemType",
                "label_cy": "Disgrifiad o sut bydd yr ased o fudd i'r gymuned",
                "substitution_group": "xbrli:item",
                "concept_id": "cic:DescriptionHowAssetWillBenefitCommunity",
                "abstract": false,
                "children": []
              },
              {
                "tree_id": "0000-0006-0006",
                "uuid": "a9b9c3ab-c722-459b-975d-dff50b3016cb",
                "qname": "cic:AssetSpecifiedInCompanysMemorandumOrArticlesAssociationTruefalse",
                "name": "Asset is specified in the company's memorandum or articles of association [true/false]",
                "xbrl_type": "booleanItemType",
                "full_type": "xbrli:booleanItemType",
                "label_cy": "Mae'r ased wedi'i nodi ym memorandwm neu yn erthyglau cymdeithasu'r cwmni [gwir/anwir]",
                "substitution_group": "xbrli:item",
                "concept_id": "cic:AssetSpecifiedInCompanysMemorandumOrArticlesAssociationTruefalse",
                "abstract": false,
                "children": []
              },
              {
                "tree_id": "0000-0006-0007",
                "uuid": "07b3aad2-89a4-43d6-8b6f-5a1f77ad77e4",
                "qname": "cic:DescriptionHowRegulatorsConsentToTransferWasGiven",
                "name": "Description of how the regulators consent to the transfer was given",
                "xbrl_type": "stringItemType",
                "full_type": "xbrli:stringItemType",
                "label_cy": "Disgrifiad o sut y rhoddodd y rheoleiddwyr gydsyniad ar gyfer y trosglwyddiad",
                "substitution_group": "xbrli:item",
                "concept_id": "cic:DescriptionHowRegulatorsConsentToTransferWasGiven",
                "abstract": false,
                "children": []
              }
            ]
          },
          {
            "tree_id": "0000-0007",
            "uuid": "afa2733c-3193-4944-abc9-42143a6f82ca",
            "qname": "cic:DividendsForFinancialYearToWhichReportRelatesHeading",
            "name": "Dividends for the financial year to which the report relates [heading]",
            "xbrl_type": "headingItemType",
            "full_type": "types:headingItemType",
            "label_cy": "Difidendau am y flwyddyn ariannol y mae'r adroddiad yn ymwneud â hi [pennawd]",
            "substitution_group": "xbrli:item",
            "concept_id": "cic:DividendsForFinancialYearToWhichReportRelatesHeading",
            "abstract": true,
            "children": [
              {
                "tree_id": "0000-0007-0000",
                "uuid": "af3201b3-34a5-4a04-b5fa-2afd20dc1f31",
                "qname": "cic:DividendsApplicableForFinancialYearToWhichReportRelatesTruefalse",
                "name": "Dividends applicable for the financial year to which the report relates [true/false]",
                "xbrl_type": "booleanItemType",
                "full_type": "xbrli:booleanItemType",
                "label_cy": "Difidendau sy'n berthnasol i'r flwyddyn ariannol y mae'r adroddiad yn ymwneud â hi [gwir/anwir]",
                "substitution_group": "xbrli:item",
                "concept_id": "cic:DividendsApplicableForFinancialYearToWhichReportRelatesTruefalse",
                "abstract": false,
                "children": []
              },
              {
                "tree_id": "0000-0007-0001",
                "uuid": "c7d127dc-1afb-41f9-adf8-ce9f9d5d347d",
                "qname": "cic:DescriptionSharesOnWhichDividendHasBeenDeclaredOrPaidHeading",
                "name": "Description of shares on which dividend has been declared or paid [heading]",
                "xbrl_type": "headingItemType",
                "full_type": "types:headingItemType",
                "label_cy": "Disgrifiad o gyfranddaliadau y mae difidend wedi'i ddatgan neu ei dalu ar eu cyfer [pennawd]",
                "substitution_group": "xbrli:item",
                "concept_id": "cic:DescriptionSharesOnWhichDividendHasBeenDeclaredOrPaidHeading",
                "abstract": true,
                "children": [
                  {
                    "tree_id": "0000-0007-0001-0000",
                    "uuid": "99b8f9a9-ce7c-45e2-a51c-eb4c23a4b0b9",
                    "qname": "cic:DescriptionClassShares",
                    "name": "Description of class of the shares",
                    "xbrl_type": "stringItemType",
                    "full_type": "xbrli:stringItemType",
                    "label_cy": "Disgrifiad o ddosbarth y cyfranddaliadau",
                    "substitution_group": "xbrli:item",
                    "concept_id": "cic:DescriptionClassShares",
                    "abstract": false,
                    "children": []
                  },
                  {
                    "tree_id": "0000-0007-0001-0001",
                    "uuid": "ace94578-3cda-4fa5-8414-5eea157bd69a",
                    "qname": "cic:NumberShares",
                    "name": "Number of shares",
                    "xbrl_type": "decimalItemType",
                    "full_type": "xbrli:decimalItemType",
                    "label_cy": "Nifer y cyfranddaliadau",
                    "substitution_group": "xbrli:item",
                    "concept_id": "cic:NumberShares",
                    "abstract": false,
                    "children": []
                  },
                  {
                    "tree_id": "0000-0007-0001-0002",
                    "uuid": "76553586-e8ac-4a39-b261-f6ff34dda05c",
                    "qname": "cic:ValueShares",
                    "name": "Value of shares",
                    "xbrl_type": "monetaryItemType",
                    "full_type": "xbrli:monetaryItemType",
                    "label_cy": "Gwerth y cyfranddaliadau",
                    "substitution_group": "xbrli:item",
                    "concept_id": "cic:ValueShares",
                    "abstract": false,
                    "children": []
                  }
                ]
              },
              {
                "tree_id": "0000-0007-0002",
                "uuid": "5b995af1-6467-44f6-9b8e-3ab501283322",
                "qname": "core:DividendPerShare",
                "name": "Dividend per share",
                "xbrl_type": "perShareItemType",
                "full_type": "num:perShareItemType",
                "label_cy": "Difidend am bob cyfranddaliad",
                "substitution_group": "xbrli:item",
                "concept_id": "core:DividendPerShare",
                "abstract": false,
                "children": []
              },
              {
                "tree_id": "0000-0007-0003",
                "uuid": "7fa5abd3-2656-4bfc-8ca2-8c9c72d0e3ed",
                "qname": "cic:DividendExemptTruefalse",
                "name": "Dividend is exempt [true/false]",
                "xbrl_type": "booleanItemType",
                "full_type": "xbrli:booleanItemType",
                "label_cy": "Mae'r difidend wedi'i eithrio [gwir/anwir]",
                "substitution_group": "xbrli:item",
                "concept_id": "cic:DividendExemptTruefalse",
                "abstract": false,
                "children": []
              },
              {
                "tree_id": "0000-0007-0004",
                "uuid": "a91819d8-0c86-4885-8417-592e2a2653da",
                "qname": "cic:DescriptionWhyDividendExempt",
                "name": "Description of why dividend is exempt",
                "xbrl_type": "stringItemType",
                "full_type": "xbrli:stringItemType",
                "label_cy": "Disgrifiad o'r rheswm pam mae'r difidend wedi'i eithrio",
                "substitution_group": "xbrli:item",
                "concept_id": "cic:DescriptionWhyDividendExempt",
                "abstract": false,
                "children": []
              },
              {
                "tree_id": "0000-0007-0005",
                "uuid": "a290d37e-4125-4098-a657-9abc9b71c348",
                "qname": "cic:DividendPerShareMaximum",
                "name": "Dividend per share, maximum",
                "xbrl_type": "perShareItemType",
                "full_type": "num:perShareItemType",
                "label_cy": "Difidend fesul cyfranddaliad, uchafswm",
                "substitution_group": "xbrli:item",
                "concept_id": "cic:DividendPerShareMaximum",
                "abstract": false,
                "children": []
              },
              {
                "tree_id": "0000-0007-0006",
                "uuid": "632cd3d5-1f2c-48a9-afe0-68a7fc3116a8",
                "qname": "cic:MaximumAggregateDividend",
                "name": "Maximum aggregate dividend",
                "xbrl_type": "monetaryItemType",
                "full_type": "xbrli:monetaryItemType",
                "label_cy": "Difidend cyfanredol uchaf",
                "substitution_group": "xbrli:item",
                "concept_id": "cic:MaximumAggregateDividend",
                "abstract": false,
                "children": []
              },
              {
                "tree_id": "0000-0007-0007",
                "uuid": "b18827ad-3868-4d83-afc6-68e8bea449fa",
                "qname": "cic:TotalAmountAllExemptDividend",
                "name": "Total amount of all exempt dividend",
                "xbrl_type": "monetaryItemType",
                "full_type": "xbrli:monetaryItemType",
                "label_cy": "Cyfanswm yr holl ddifidendau wedi'u heithrio",
                "substitution_group": "xbrli:item",
                "concept_id": "cic:TotalAmountAllExemptDividend",
                "abstract": false,
                "children": []
              },
              {
                "tree_id": "0000-0007-0008",
                "uuid": "6a4901e9-850b-459f-9a30-a9ae6862e022",
                "qname": "cic:TotalAmountAllNon-exemptDividend",
                "name": "Total amount of all non-exempt dividend",
                "xbrl_type": "monetaryItemType",
                "full_type": "xbrli:monetaryItemType",
                "label_cy": "Cyfanswm yr holl ddifidendau nad ydynt wedi'u heithrio",
                "substitution_group": "xbrli:item",
                "concept_id": "cic:TotalAmountAllNon-exemptDividend",
                "abstract": false,
                "children": []
              }
            ]
          },
          {
            "tree_id": "0000-0008",
            "uuid": "55fbf3dc-1f05-4263-a06f-07f9e7f74a94",
            "qname": "cic:InterestPaidPerformance-relatedRateHeading",
            "name": "Interest paid at a performance-related rate [heading]",
            "xbrl_type": "headingItemType",
            "full_type": "types:headingItemType",
            "label_cy": "Llog a dalwyd ar gyfradd sy'n gysylltiedig â pherfformiad [pennawd]",
            "substitution_group": "xbrli:item",
            "concept_id": "cic:InterestPaidPerformance-relatedRateHeading",
            "abstract": true,
            "children": [
              {
                "tree_id": "0000-0008-0000",
                "uuid": "617b118a-23ca-4e4e-9277-15f5e7230ddb",
                "qname": "cic:InterestPaidPerformance-relatedRateTruefalse",
                "name": "Interest paid at a performance-related rate [true/false]",
                "xbrl_type": "booleanItemType",
                "full_type": "xbrli:booleanItemType",
                "label_cy": "Llog a dalwyd ar gyfradd sy'n gysylltiedig â pherfformiad [gwir/anwir]",
                "substitution_group": "xbrli:item",
                "concept_id": "cic:InterestPaidPerformance-relatedRateTruefalse",
                "abstract": false,
                "children": []
              },
              {
                "tree_id": "0000-0008-0001",
                "uuid": "e8d8829d-3506-4c16-bfcf-dacf05512a06",
                "qname": "core:EffectiveInterestRateOnBorrowings",
                "name": "Effective interest rate on borrowings",
                "xbrl_type": "percentItemType",
                "full_type": "num:percentItemType",
                "label_cy": "Cyfradd llog effeithiol ar fenthyciadau",
                "substitution_group": "xbrli:item",
                "concept_id": "core:EffectiveInterestRateOnBorrowings",
                "abstract": false,
                "children": [
                  {
                    "tree_id": "0000-0008-0001-0000",
                    "uuid": "b3ce3102-05cc-423a-a5bc-698bcceb817a",
                    "qname": "core:EffectiveInterestRateOnBankBorrowings",
                    "name": "Effective interest rate on bank borrowings",
                    "xbrl_type": "percentItemType",
                    "full_type": "num:percentItemType",
                    "label_cy": "Cyfradd llog effeithiol ar fenthyciadau banc",
                    "substitution_group": "xbrli:item",
                    "concept_id": "core:EffectiveInterestRateOnBankBorrowings",
                    "abstract": false,
                    "children": []
                  },
                  {
                    "tree_id": "0000-0008-0001-0001",
                    "uuid": "a16e40f7-dced-447b-aad1-db2917fc9de3",
                    "qname": "core:EffectiveInterestRateOnBankOverdrafts",
                    "name": "Effective interest rate on bank overdrafts",
                    "xbrl_type": "percentItemType",
                    "full_type": "num:percentItemType",
                    "label_cy": "Cyfradd llog effeithiol ar orddrafftiau banc",
                    "substitution_group": "xbrli:item",
                    "concept_id": "core:EffectiveInterestRateOnBankOverdrafts",
                    "abstract": false,
                    "children": []
                  }
                ]
              },
              {
                "tree_id": "0000-0008-0002",
                "uuid": "e59048d3-fd7b-48ef-8ee4-843b4f7fbce1",
                "qname": "cic:InterestCapAppliesToDebtTruefalse",
                "name": "Interest cap applies to debt [true/false]",
                "xbrl_type": "booleanItemType",
                "full_type": "xbrli:booleanItemType",
                "label_cy": "Mae'r cap ar log yn berthnasol i ddyled [gwir/anwir]",
                "substitution_group": "xbrli:item",
                "concept_id": "cic:InterestCapAppliesToDebtTruefalse",
                "abstract": false,
                "children": []
              },
              {
                "tree_id": "0000-0008-0003",
                "uuid": "bbf9a707-b0c1-4e6d-a67d-978d03c8e741",
                "qname": "core:DescriptionBorrowings",
                "name": "Description of borrowings",
                "xbrl_type": "stringItemType",
                "full_type": "xbrli:stringItemType",
                "label_cy": "Disgrifiad o fenthyciadau",
                "substitution_group": "xbrli:item",
                "concept_id": "core:DescriptionBorrowings",
                "abstract": false,
                "children": []
              },
              {
                "tree_id": "0000-0008-0004",
                "uuid": "dff8a90c-138f-402e-98c4-1a66ebefba9d",
                "qname": "cic:InterestCapValueApplicable",
                "name": "Interest cap value applicable",
                "xbrl_type": "percentItemType",
                "full_type": "num:percentItemType",
                "label_cy": "Mae gwerth y cap ar log yn berthnasol",
                "substitution_group": "xbrli:item",
                "concept_id": "cic:InterestCapValueApplicable",
                "abstract": false,
                "children": []
              },
              {
                "tree_id": "0000-0008-0005",
                "uuid": "3cc2fe94-fdef-4d95-892e-5509598ac5e9",
                "qname": "cic:DescriptionWhyInterestCapDoesNotApply",
                "name": "Description of why interest cap does not apply",
                "xbrl_type": "stringItemType",
                "full_type": "xbrli:stringItemType",
                "label_cy": "Disgrifiad o'r rheswm pam nad yw'r cap ar log yn berthnasol",
                "substitution_group": "xbrli:item",
                "concept_id": "cic:DescriptionWhyInterestCapDoesNotApply",
                "abstract": false,
                "children": []
              }
            ]
          },
          {
            "tree_id": "0000-0009",
            "uuid": "1544bfb9-147d-4064-a36e-89f2142e62bf",
            "qname": "cic:SignatoryHeading",
            "name": "Signatory [heading]",
            "xbrl_type": "headingItemType",
            "full_type": "types:headingItemType",
            "label_cy": "Llofnodwr [pennawd]",
            "substitution_group": "xbrli:item",
            "concept_id": "cic:SignatoryHeading",
            "abstract": true,
            "children": [
              {
                "tree_id": "0000-0009-0000",
                "uuid": "16979d7c-0cfc-4afa-b271-ed45f8868f08",
                "qname": "cic:DirectorSigningCIC34Report",
                "name": "Director signing CIC 34 Report",
                "xbrl_type": "fixedItemType",
                "full_type": "types:fixedItemType",
                "label_cy": "Cyfarwyddwr sy'n llofnodi Adroddiad CIC 34",
                "substitution_group": "xbrli:item",
                "concept_id": "cic:DirectorSigningCIC34Report",
                "abstract": false,
                "children": []
              },
              {
                "tree_id": "0000-0009-0001",
                "uuid": "13dc19a5-1875-4fa5-9c14-588dd2063d6f",
                "qname": "cic:DateSigningCIC34Report",
                "name": "Date of signing of CIC 34 Report",
                "xbrl_type": "dateItemType",
                "full_type": "xbrli:dateItemType",
                "label_cy": "Dyddiad llofnodi Adroddiad CIC 34",
                "substitution_group": "xbrli:item",
                "concept_id": "cic:DateSigningCIC34Report",
                "abstract": false,
                "children": []
              }
            ]
          }
        ]
      }
    ]
  }
]